README.md
pyproject.toml
setup.py
django_ag_grid/__init__.py
django_ag_grid.egg-info/PKG-INFO
django_ag_grid.egg-info/SOURCES.txt
django_ag_grid.egg-info/dependency_links.txt
django_ag_grid.egg-info/top_level.txt