Metadata-Version: 2.1
Name: django-ag-grid
Version: 0.0.1
Summary: Reserved package name for django-ag-grid.
Author: django-ag-grid Maintainer
Author-email: django-ag-grid Maintainer <email@example.com>
License: MIT
Classifier: Programming Language :: Python :: 3
Classifier: License :: OSI Approved :: MIT License
Classifier: Operating System :: OS Independent
Requires-Python: >=3.7
